{
  "_format": "hh-sol-cache-2",
  "files": {
    "D:\\WebStormProjects\\harhat-demo\\contracts\\Token.sol": {
      "lastModificationDate": 1623217270726,
      "contentHash": "a25f71c42e605022a84b50f67bc9d589",
      "sourceName": "contracts/Token.sol",
      "solcConfig": {
        "version": "0.8.0",
        "settings": {
          "optimizer": {
            "enabled": false,
            "runs": 200
          },
          "outputSelection": {
            "*": {
              "*": [
                "abi",
                "evm.bytecode",
                "evm.deployedBytecode",
                "evm.methodIdentifiers"
              ],
              "": [
                "ast"
              ]
            }
          }
        }
      },
      "imports": [],
      "versionPragmas": [
        "^0.8.0"
      ],
      "artifacts": [
        "Token"
      ]
    }
  }
}
